checkmatelib/__init__.py
checkmatelib/_response.py
checkmatelib/client.py
checkmatelib/exceptions.py
checkmatelib/resource/__init__.py
checkmatelib/resource/response_schema.json
checkmatelib/resource/data/public_suffix_list.dat
checkmatelib/resource/data/valid_top_level_domains.txt
checkmatelib/url/__init__.py
checkmatelib/url/canonicalize.py
checkmatelib/url/expand.py
checkmatelib/url/hash.py
checkmatelib/url/domain/__init__.py
checkmatelib/url/domain/_data.py
checkmatelib/url/domain/_domain_core.py
checkmatelib/url/domain/domain.py
checkmatelib/url/domain/enums.py
checkmatelib/url/domain/public_suffix.py
checkmatelib/url/domain/top_level_domain.py
checkmatelib-1.0.18.dist-info/LICENSE
checkmatelib-1.0.18.dist-info/METADATA
checkmatelib-1.0.18.dist-info/WHEEL
checkmatelib-1.0.18.dist-info/top_level.txt
checkmatelib-1.0.18.dist-info/RECORD
