Metadata-Version: 2.2
Name: checkmatelib
Version: 1.0.18
Summary: Tools for interacting with the Checkmate URL checking service.
Home-page: https://github.com/hypothesis/checkmatelib
Project-URL: Bug Tracker, https://github.com/hypothesis/checkmatelib/issues
Project-URL: Changelog, https://github.com/hypothesis/checkmatelib/releases
Classifier: Programming Language :: Python :: 3
Classifier: License :: OSI Approved :: BSD License
Classifier: Intended Audience :: Developers
Requires-Python: >=3.9
License-File: LICENSE
Requires-Dist: requests
Requires-Dist: jsonschema
Requires-Dist: importlib_resources
Requires-Dist: netaddr>1.0.0
